flask_tinydb/__init__.py
flask_tinydb/py.typed
flask_tinydb/storages.py
flask_tinydb/tinydb.py
Flask_tinydb-1.3.0.dist-info/LICENSE.rst
Flask_tinydb-1.3.0.dist-info/METADATA
Flask_tinydb-1.3.0.dist-info/WHEEL
Flask_tinydb-1.3.0.dist-info/top_level.txt
Flask_tinydb-1.3.0.dist-info/RECORD
